{
  "fio version" : "fio-3.35",
  "timestamp" : 1701642251,
  "timestamp_ms" : 1701642251516,
  "time" : "Sun Dec  3 22:24:11 2023",
  "global options" : {
    "ioengine" : "io_uring",
    "size" : "813z",
    "bs" : "64K",
    "direct" : "1",
    "group_reporting" : "0",
    "zonemode" : "zbd",
    "thread" : "1",
    "lat_percentiles" : "1",
    "filename" : "/dev/nvme0n2"
  },
  "jobs" : [
    {
      "jobname" : "fill-prep",
      "groupid" : 0,
      "error" : 0,
      "eta" : 0,
      "elapsed" : 874,
      "job options" : {
        "iodepth" : "1",
        "rw" : "write",
        "numjobs" : "1"
      },
      "read" : {
        "io_bytes" : 0,
        "io_kbytes" : 0,
        "bw_bytes" : 0,
        "bw" : 0,
        "iops" : 0.000000,
        "runtime" : 0,
        "total_ios" : 0,
        "short_ios" : 0,
        "drop_ios" : 0,
        "slat_ns" : {
          "min" : 0,
          "max" : 0,
          "mean" : 0.000000,
          "stddev" : 0.000000,
          "N" : 0
        },
        "clat_ns" : {
          "min" : 0,
          "max" : 0,
          "mean" : 0.000000,
          "stddev" : 0.000000,
          "N" : 0
        },
        "lat_ns" : {
          "min" : 0,
          "max" : 0,
          "mean" : 0.000000,
          "stddev" : 0.000000,
          "N" : 0
        },
        "bw_min" : 0,
        "bw_max" : 0,
        "bw_agg" : 0.000000,
        "bw_mean" : 0.000000,
        "bw_dev" : 0.000000,
        "bw_samples" : 0,
        "iops_min" : 0,
        "iops_max" : 0,
        "iops_mean" : 0.000000,
        "iops_stddev" : 0.000000,
        "iops_samples" : 0
      },
      "finish" : {
        "total_zone_resets" : 0,
        "io_bytes" : 918134194176,
        "io_kbytes" : 896615424,
        "bw_bytes" : 1086024965,
        "bw" : 1060571,
        "iops" : 16571.425868,
        "runtime" : 845408,
        "total_ios" : 14009616,
        "short_ios" : 0,
        "drop_ios" : 0,
        "slat_ns" : {
          "min" : 7850,
          "max" : 19190215,
          "mean" : 10472.888596,
          "stddev" : 6330.520730,
          "N" : 14009616
        },
        "clat_ns" : {
          "min" : 803,
          "max" : 28973404,
          "mean" : 48791.864207,
          "stddev" : 17427.688732,
          "N" : 14009616,
          "percentile" : {
            "1.000000" : 44288,
            "5.000000" : 45312,
            "10.000000" : 45824,
            "20.000000" : 46848,
            "30.000000" : 47360,
            "40.000000" : 47872,
            "50.000000" : 47872,
            "60.000000" : 48384,
            "70.000000" : 48896,
            "80.000000" : 49408,
            "90.000000" : 50944,
            "95.000000" : 52480,
            "99.000000" : 68096,
            "99.500000" : 72192,
            "99.900000" : 97792,
            "99.950000" : 128512,
            "99.990000" : 618496
          }
        },
        "lat_ns" : {
          "min" : 51909,
          "max" : 28983554,
          "mean" : 59264.752803,
          "stddev" : 18673.445314,
          "N" : 14009616,
          "percentile" : {
            "1.000000" : 54016,
            "5.000000" : 55552,
            "10.000000" : 56064,
            "20.000000" : 57088,
            "30.000000" : 57600,
            "40.000000" : 58112,
            "50.000000" : 58112,
            "60.000000" : 58624,
            "70.000000" : 59136,
            "80.000000" : 60160,
            "90.000000" : 62720,
            "95.000000" : 63744,
            "99.000000" : 78336,
            "99.500000" : 82432,
            "99.900000" : 111104,
            "99.950000" : 142336,
            "99.990000" : 634880
          }
        },
        "bw_min" : 940633,
        "bw_max" : 1101723,
        "bw_agg" : 100.000000,
        "bw_mean" : 1061390.112426,
        "bw_dev" : 22475.484899,
        "bw_samples" : 1690,
        "iops_min" : 14697,
        "iops_max" : 17214,
        "iops_mean" : 16584.027811,
        "iops_stddev" : 351.194590,
        "iops_samples" : 1690
      },
      "ZNS Reset" : {
        "total_zone_resets" : 0,
        "io_bytes" : 0,
        "io_kbytes" : 0,
        "bw_bytes" : 0,
        "bw" : 0,
        "iops" : 0.000000,
        "runtime" : 0,
        "total_ios" : 0,
        "short_ios" : 0,
        "drop_ios" : 0,
        "slat_ns" : {
          "min" : 0,
          "max" : 0,
          "mean" : 0.000000,
          "stddev" : 0.000000,
          "N" : 0
        },
        "clat_ns" : {
          "min" : 0,
          "max" : 0,
          "mean" : 0.000000,
          "stddev" : 0.000000,
          "N" : 0
        },
        "lat_ns" : {
          "min" : 0,
          "max" : 0,
          "mean" : 0.000000,
          "stddev" : 0.000000,
          "N" : 0
        },
        "bw_min" : 0,
        "bw_max" : 0,
        "bw_agg" : 0.000000,
        "bw_mean" : 0.000000,
        "bw_dev" : 0.000000,
        "bw_samples" : 0,
        "iops_min" : 0,
        "iops_max" : 0,
        "iops_mean" : 0.000000,
        "iops_stddev" : 0.000000,
        "iops_samples" : 0
      },
      "sync" : {
        "total_ios" : 0,
        "lat_ns" : {
          "min" : 0,
          "max" : 0,
          "mean" : 0.000000,
          "stddev" : 0.000000,
          "N" : 0
        }
      },
      "job_runtime" : 845407,
      "usr_cpu" : 7.158091,
      "sys_cpu" : 16.832603,
      "ctx" : 28019413,
      "majf" : 0,
      "minf" : 0,
      "iodepth_level" : {
        "1" : 100.000000,
        "2" : 0.000000,
        "4" : 0.000000,
        "8" : 0.000000,
        "16" : 0.000000,
        "32" : 0.000000,
        ">=64" : 0.000000
      },
      "iodepth_submit" : {
        "0" : 0.000000,
        "4" : 100.000000,
        "8" : 0.000000,
        "16" : 0.000000,
        "32" : 0.000000,
        "64" : 0.000000,
        ">=64" : 0.000000
      },
      "iodepth_complete" : {
        "0" : 0.000000,
        "4" : 100.000000,
        "8" : 0.000000,
        "16" : 0.000000,
        "32" : 0.000000,
        "64" : 0.000000,
        ">=64" : 0.000000
      },
      "latency_ns" : {
        "2" : 0.000000,
        "4" : 0.000000,
        "10" : 0.000000,
        "20" : 0.000000,
        "50" : 0.000000,
        "100" : 0.000000,
        "250" : 0.000000,
        "500" : 0.000000,
        "750" : 0.000000,
        "1000" : 0.010000
      },
      "latency_us" : {
        "2" : 0.010000,
        "4" : 0.010000,
        "10" : 0.010000,
        "20" : 0.010000,
        "50" : 85.833359,
        "100" : 14.071399,
        "250" : 0.060423,
        "500" : 0.010000,
        "750" : 0.023548,
        "1000" : 0.010000
      },
      "latency_ms" : {
        "2" : 0.010000,
        "4" : 0.010000,
        "10" : 0.010000,
        "20" : 0.010000,
        "50" : 0.010000,
        "100" : 0.000000,
        "250" : 0.000000,
        "500" : 0.000000,
        "750" : 0.000000,
        "1000" : 0.000000,
        "2000" : 0.000000,
        ">=2000" : 0.000000
      },
      "latency_depth" : 1,
      "latency_target" : 0,
      "latency_percentile" : 100.000000,
      "latency_window" : 0
    },
    {
      "jobname" : "trim",
      "groupid" : 1,
      "error" : 0,
      "eta" : 0,
      "elapsed" : 874,
      "job options" : {
        "rw" : "randtrim",
        "iodepth" : "1",
        "numjobs" : "1",
        "bs" : "2147483648",
        "rate" : ",,62042991939.50",
        "runtime" : "1m",
        "exit_what" : "stonewall"
      },
      "read" : {
        "io_bytes" : 0,
        "io_kbytes" : 0,
        "bw_bytes" : 0,
        "bw" : 0,
        "iops" : 0.000000,
        "runtime" : 0,
        "total_ios" : 0,
        "short_ios" : 0,
        "drop_ios" : 0,
        "slat_ns" : {
          "min" : 0,
          "max" : 0,
          "mean" : 0.000000,
          "stddev" : 0.000000,
          "N" : 0
        },
        "clat_ns" : {
          "min" : 0,
          "max" : 0,
          "mean" : 0.000000,
          "stddev" : 0.000000,
          "N" : 0
        },
        "lat_ns" : {
          "min" : 0,
          "max" : 0,
          "mean" : 0.000000,
          "stddev" : 0.000000,
          "N" : 0
        },
        "bw_min" : 0,
        "bw_max" : 0,
        "bw_agg" : 0.000000,
        "bw_mean" : 0.000000,
        "bw_dev" : 0.000000,
        "bw_samples" : 0,
        "iops_min" : 0,
        "iops_max" : 0,
        "iops_mean" : 0.000000,
        "iops_stddev" : 0.000000,
        "iops_samples" : 0
      },
      "finish" : {
        "total_zone_resets" : 813,
        "io_bytes" : 0,
        "io_kbytes" : 0,
        "bw_bytes" : 0,
        "bw" : 0,
        "iops" : 0.000000,
        "runtime" : 0,
        "total_ios" : 0,
        "short_ios" : 0,
        "drop_ios" : 0,
        "slat_ns" : {
          "min" : 0,
          "max" : 0,
          "mean" : 0.000000,
          "stddev" : 0.000000,
          "N" : 0
        },
        "clat_ns" : {
          "min" : 0,
          "max" : 0,
          "mean" : 0.000000,
          "stddev" : 0.000000,
          "N" : 0
        },
        "lat_ns" : {
          "min" : 0,
          "max" : 0,
          "mean" : 0.000000,
          "stddev" : 0.000000,
          "N" : 0
        },
        "bw_min" : 0,
        "bw_max" : 0,
        "bw_agg" : 0.000000,
        "bw_mean" : 0.000000,
        "bw_dev" : 0.000000,
        "bw_samples" : 0,
        "iops_min" : 0,
        "iops_max" : 0,
        "iops_mean" : 0.000000,
        "iops_stddev" : 0.000000,
        "iops_samples" : 0
      },
      "ZNS Reset" : {
        "total_zone_resets" : 813,
        "io_bytes" : 1745904205824,
        "io_kbytes" : 1704984576,
        "bw_bytes" : 62069973187,
        "bw" : 60615208,
        "iops" : 28.903584,
        "runtime" : 28128,
        "total_ios" : 813,
        "short_ios" : 0,
        "drop_ios" : 0,
        "slat_ns" : {
          "min" : 0,
          "max" : 0,
          "mean" : 0.000000,
          "stddev" : 0.000000,
          "N" : 0
        },
        "clat_ns" : {
          "min" : 18447040,
          "max" : 21759068,
          "mean" : 19070571.253383,
          "stddev" : 549003.733406,
          "N" : 813,
          "percentile" : {
            "1.000000" : 18481152,
            "5.000000" : 18743296,
            "10.000000" : 18743296,
            "20.000000" : 18743296,
            "30.000000" : 19005440,
            "40.000000" : 19005440,
            "50.000000" : 19005440,
            "60.000000" : 19005440,
            "70.000000" : 19005440,
            "80.000000" : 19005440,
            "90.000000" : 19267584,
            "95.000000" : 20578304,
            "99.000000" : 21626880,
            "99.500000" : 21626880,
            "99.900000" : 21889024,
            "99.950000" : 21889024,
            "99.990000" : 21889024
          }
        },
        "lat_ns" : {
          "min" : 18448213,
          "max" : 21760190,
          "mean" : 19071538.595326,
          "stddev" : 548992.624376,
          "N" : 813,
          "percentile" : {
            "1.000000" : 18481152,
            "5.000000" : 18743296,
            "10.000000" : 18743296,
            "20.000000" : 18743296,
            "30.000000" : 19005440,
            "40.000000" : 19005440,
            "50.000000" : 19005440,
            "60.000000" : 19005440,
            "70.000000" : 19005440,
            "80.000000" : 19005440,
            "90.000000" : 19267584,
            "95.000000" : 20578304,
            "99.000000" : 21626880,
            "99.500000" : 21626880,
            "99.900000" : 21889024,
            "99.950000" : 21889024,
            "99.990000" : 21889024
          }
        },
        "bw_min" : 58720256,
        "bw_max" : 62914560,
        "bw_agg" : 100.000000,
        "bw_mean" : 60667611.428571,
        "bw_dev" : 2110725.941059,
        "bw_samples" : 56,
        "iops_min" : 28,
        "iops_max" : 30,
        "iops_mean" : 28.928571,
        "iops_stddev" : 1.006473,
        "iops_samples" : 56
      },
      "sync" : {
        "total_ios" : 0,
        "lat_ns" : {
          "min" : 0,
          "max" : 0,
          "mean" : 0.000000,
          "stddev" : 0.000000,
          "N" : 0
        }
      },
      "job_runtime" : 28127,
      "usr_cpu" : 0.103104,
      "sys_cpu" : 0.167099,
      "ctx" : 2431,
      "majf" : 0,
      "minf" : 0,
      "iodepth_level" : {
        "1" : 100.000000,
        "2" : 0.000000,
        "4" : 0.000000,
        "8" : 0.000000,
        "16" : 0.000000,
        "32" : 0.000000,
        ">=64" : 0.000000
      },
      "iodepth_submit" : {
        "0" : 0.000000,
        "4" : 100.000000,
        "8" : 0.000000,
        "16" : 0.000000,
        "32" : 0.000000,
        "64" : 0.000000,
        ">=64" : 0.000000
      },
      "iodepth_complete" : {
        "0" : 0.000000,
        "4" : 100.000000,
        "8" : 0.000000,
        "16" : 0.000000,
        "32" : 0.000000,
        "64" : 0.000000,
        ">=64" : 0.000000
      },
      "latency_ns" : {
        "2" : 0.000000,
        "4" : 0.000000,
        "10" : 0.000000,
        "20" : 0.000000,
        "50" : 0.000000,
        "100" : 0.000000,
        "250" : 0.000000,
        "500" : 0.000000,
        "750" : 0.000000,
        "1000" : 0.000000
      },
      "latency_us" : {
        "2" : 0.000000,
        "4" : 0.000000,
        "10" : 0.000000,
        "20" : 0.000000,
        "50" : 0.000000,
        "100" : 0.000000,
        "250" : 0.000000,
        "500" : 0.000000,
        "750" : 0.000000,
        "1000" : 0.000000
      },
      "latency_ms" : {
        "2" : 0.000000,
        "4" : 0.000000,
        "10" : 0.000000,
        "20" : 94.464945,
        "50" : 5.535055,
        "100" : 0.000000,
        "250" : 0.000000,
        "500" : 0.000000,
        "750" : 0.000000,
        "1000" : 0.000000,
        "2000" : 0.000000,
        ">=2000" : 0.000000
      },
      "latency_depth" : 1,
      "latency_target" : 0,
      "latency_percentile" : 100.000000,
      "latency_window" : 0
    },
    {
      "jobname" : "write",
      "groupid" : 1,
      "error" : 0,
      "eta" : 0,
      "elapsed" : 874,
      "job options" : {
        "rw" : "write",
        "iodepth" : "1",
        "size" : "91z",
        "offset" : "813z",
        "offset_increment" : "91z",
        "numjobs" : "1",
        "bs" : "8K",
        "runtime" : "1m",
        "exit_what" : "stonewall"
      },
      "read" : {
        "io_bytes" : 0,
        "io_kbytes" : 0,
        "bw_bytes" : 0,
        "bw" : 0,
        "iops" : 0.000000,
        "runtime" : 0,
        "total_ios" : 0,
        "short_ios" : 0,
        "drop_ios" : 0,
        "slat_ns" : {
          "min" : 0,
          "max" : 0,
          "mean" : 0.000000,
          "stddev" : 0.000000,
          "N" : 0
        },
        "clat_ns" : {
          "min" : 0,
          "max" : 0,
          "mean" : 0.000000,
          "stddev" : 0.000000,
          "N" : 0
        },
        "lat_ns" : {
          "min" : 0,
          "max" : 0,
          "mean" : 0.000000,
          "stddev" : 0.000000,
          "N" : 0
        },
        "bw_min" : 0,
        "bw_max" : 0,
        "bw_agg" : 0.000000,
        "bw_mean" : 0.000000,
        "bw_dev" : 0.000000,
        "bw_samples" : 0,
        "iops_min" : 0,
        "iops_max" : 0,
        "iops_mean" : 0.000000,
        "iops_stddev" : 0.000000,
        "iops_samples" : 0
      },
      "finish" : {
        "total_zone_resets" : 0,
        "io_bytes" : 8505384960,
        "io_kbytes" : 8306040,
        "bw_bytes" : 302381433,
        "bw" : 295294,
        "iops" : 36911.796075,
        "runtime" : 28128,
        "total_ios" : 1038255,
        "short_ios" : 0,
        "drop_ios" : 0,
        "slat_ns" : {
          "min" : 6394,
          "max" : 986218,
          "mean" : 7876.005452,
          "stddev" : 1524.799214,
          "N" : 1038255
        },
        "clat_ns" : {
          "min" : 714,
          "max" : 704901,
          "mean" : 18217.948685,
          "stddev" : 1895.132169,
          "N" : 1038255,
          "percentile" : {
            "1.000000" : 14912,
            "5.000000" : 15424,
            "10.000000" : 15936,
            "20.000000" : 17280,
            "30.000000" : 17536,
            "40.000000" : 18048,
            "50.000000" : 18560,
            "60.000000" : 18816,
            "70.000000" : 19072,
            "80.000000" : 19328,
            "90.000000" : 19584,
            "95.000000" : 19840,
            "99.000000" : 21632,
            "99.500000" : 23424,
            "99.900000" : 29312,
            "99.950000" : 35584,
            "99.990000" : 55552
          }
        },
        "lat_ns" : {
          "min" : 19199,
          "max" : 1008137,
          "mean" : 26093.954137,
          "stddev" : 2455.179708,
          "N" : 1038255,
          "percentile" : {
            "1.000000" : 22400,
            "5.000000" : 22912,
            "10.000000" : 23424,
            "20.000000" : 24960,
            "30.000000" : 25472,
            "40.000000" : 25728,
            "50.000000" : 26240,
            "60.000000" : 26496,
            "70.000000" : 26752,
            "80.000000" : 27008,
            "90.000000" : 27520,
            "95.000000" : 29312,
            "99.000000" : 30848,
            "99.500000" : 33024,
            "99.900000" : 39680,
            "99.950000" : 45312,
            "99.990000" : 68096
          }
        },
        "bw_min" : 258064,
        "bw_max" : 315008,
        "bw_agg" : 100.000000,
        "bw_mean" : 295626.000000,
        "bw_dev" : 10339.207861,
        "bw_samples" : 56,
        "iops_min" : 32258,
        "iops_max" : 39376,
        "iops_mean" : 36953.250000,
        "iops_stddev" : 1292.409367,
        "iops_samples" : 56
      },
      "ZNS Reset" : {
        "total_zone_resets" : 0,
        "io_bytes" : 0,
        "io_kbytes" : 0,
        "bw_bytes" : 0,
        "bw" : 0,
        "iops" : 0.000000,
        "runtime" : 0,
        "total_ios" : 0,
        "short_ios" : 0,
        "drop_ios" : 0,
        "slat_ns" : {
          "min" : 0,
          "max" : 0,
          "mean" : 0.000000,
          "stddev" : 0.000000,
          "N" : 0
        },
        "clat_ns" : {
          "min" : 0,
          "max" : 0,
          "mean" : 0.000000,
          "stddev" : 0.000000,
          "N" : 0
        },
        "lat_ns" : {
          "min" : 0,
          "max" : 0,
          "mean" : 0.000000,
          "stddev" : 0.000000,
          "N" : 0
        },
        "bw_min" : 0,
        "bw_max" : 0,
        "bw_agg" : 0.000000,
        "bw_mean" : 0.000000,
        "bw_dev" : 0.000000,
        "bw_samples" : 0,
        "iops_min" : 0,
        "iops_max" : 0,
        "iops_mean" : 0.000000,
        "iops_stddev" : 0.000000,
        "iops_samples" : 0
      },
      "sync" : {
        "total_ios" : 0,
        "lat_ns" : {
          "min" : 0,
          "max" : 0,
          "mean" : 0.000000,
          "stddev" : 0.000000,
          "N" : 0
        }
      },
      "job_runtime" : 28127,
      "usr_cpu" : 10.772567,
      "sys_cpu" : 32.054609,
      "ctx" : 2076141,
      "majf" : 0,
      "minf" : 0,
      "iodepth_level" : {
        "1" : 100.000000,
        "2" : 0.000000,
        "4" : 0.000000,
        "8" : 0.000000,
        "16" : 0.000000,
        "32" : 0.000000,
        ">=64" : 0.000000
      },
      "iodepth_submit" : {
        "0" : 0.000000,
        "4" : 100.000000,
        "8" : 0.000000,
        "16" : 0.000000,
        "32" : 0.000000,
        "64" : 0.000000,
        ">=64" : 0.000000
      },
      "iodepth_complete" : {
        "0" : 0.000000,
        "4" : 100.000000,
        "8" : 0.000000,
        "16" : 0.000000,
        "32" : 0.000000,
        "64" : 0.000000,
        ">=64" : 0.000000
      },
      "latency_ns" : {
        "2" : 0.000000,
        "4" : 0.000000,
        "10" : 0.000000,
        "20" : 0.000000,
        "50" : 0.000000,
        "100" : 0.000000,
        "250" : 0.000000,
        "500" : 0.000000,
        "750" : 0.010000,
        "1000" : 0.023790
      },
      "latency_us" : {
        "2" : 0.010000,
        "4" : 0.010000,
        "10" : 0.015410,
        "20" : 96.081791,
        "50" : 3.858012,
        "100" : 0.013773,
        "250" : 0.010000,
        "500" : 0.010000,
        "750" : 0.010000,
        "1000" : 0.000000
      },
      "latency_ms" : {
        "2" : 0.000000,
        "4" : 0.000000,
        "10" : 0.000000,
        "20" : 0.000000,
        "50" : 0.000000,
        "100" : 0.000000,
        "250" : 0.000000,
        "500" : 0.000000,
        "750" : 0.000000,
        "1000" : 0.000000,
        "2000" : 0.000000,
        ">=2000" : 0.000000
      },
      "latency_depth" : 1,
      "latency_target" : 0,
      "latency_percentile" : 100.000000,
      "latency_window" : 0
    }
  ],
  "disk_util" : [
    {
      "name" : "nvme0n2",
      "read_ios" : 66,
      "write_ios" : 15045336,
      "read_sectors" : 3776,
      "write_sectors" : 1809789408,
      "read_merges" : 0,
      "write_merges" : 0,
      "read_ticks" : 4,
      "write_ticks" : 724886,
      "in_queue" : 724890,
      "util" : 100.000000
    }
  ]
}
