{
  "fio version" : "fio-3.35",
  "timestamp" : 1693365949,
  "timestamp_ms" : 1693365949119,
  "time" : "Wed Aug 30 03:25:49 2023",
  "global options" : {
    "name" : "loaded-reset",
    "ioengine" : "io_uring_cmd",
    "size" : "1023z",
    "bs" : "64K",
    "zonemode" : "zbd",
    "thread" : "1",
    "lat_percentiles" : "1",
    "filename" : "/dev/ng0n1",
    "sqthread_poll" : "1"
  },
  "jobs" : [
    {
      "jobname" : "fill-prep",
      "groupid" : 0,
      "error" : 0,
      "eta" : 0,
      "elapsed" : 592,
      "job options" : {
        "iodepth" : "1",
        "rw" : "write"
      },
      "read" : {
        "io_bytes" : 0,
        "io_kbytes" : 0,
        "bw_bytes" : 0,
        "bw" : 0,
        "iops" : 0.000000,
        "runtime" : 0,
        "total_ios" : 0,
        "short_ios" : 0,
        "drop_ios" : 0,
        "slat_ns" : {
          "min" : 0,
          "max" : 0,
          "mean" : 0.000000,
          "stddev" : 0.000000,
          "N" : 0
        },
        "clat_ns" : {
          "min" : 0,
          "max" : 0,
          "mean" : 0.000000,
          "stddev" : 0.000000,
          "N" : 0
        },
        "lat_ns" : {
          "min" : 0,
          "max" : 0,
          "mean" : 0.000000,
          "stddev" : 0.000000,
          "N" : 0
        },
        "bw_min" : 0,
        "bw_max" : 0,
        "bw_agg" : 0.000000,
        "bw_mean" : 0.000000,
        "bw_dev" : 0.000000,
        "bw_samples" : 0,
        "iops_min" : 0,
        "iops_max" : 0,
        "iops_mean" : 0.000000,
        "iops_stddev" : 0.000000,
        "iops_samples" : 0
      },
      "write" : {
        "io_bytes" : 68652367872,
        "io_kbytes" : 67043328,
        "bw_bytes" : 116494605,
        "bw" : 113764,
        "iops" : 1777.566611,
        "runtime" : 589318,
        "total_ios" : 1047552,
        "short_ios" : 0,
        "drop_ios" : 0,
        "slat_ns" : {
          "min" : 0,
          "max" : 0,
          "mean" : 0.000000,
          "stddev" : 0.000000,
          "N" : 0
        },
        "clat_ns" : {
          "min" : 501811,
          "max" : 7090263,
          "mean" : 559622.161341,
          "stddev" : 54941.761890,
          "N" : 1047552,
          "percentile" : {
            "1.000000" : 552960,
            "5.000000" : 552960,
            "10.000000" : 552960,
            "20.000000" : 552960,
            "30.000000" : 552960,
            "40.000000" : 552960,
            "50.000000" : 552960,
            "60.000000" : 552960,
            "70.000000" : 561152,
            "80.000000" : 561152,
            "90.000000" : 561152,
            "95.000000" : 561152,
            "99.000000" : 569344,
            "99.500000" : 577536,
            "99.900000" : 1384448,
            "99.950000" : 1712128,
            "99.990000" : 2670592
          }
        },
        "lat_ns" : {
          "min" : 531678,
          "max" : 7091911,
          "mean" : 562017.791963,
          "stddev" : 55009.877491,
          "N" : 1047552,
          "percentile" : {
            "1.000000" : 552960,
            "5.000000" : 561152,
            "10.000000" : 561152,
            "20.000000" : 561152,
            "30.000000" : 561152,
            "40.000000" : 561152,
            "50.000000" : 561152,
            "60.000000" : 561152,
            "70.000000" : 561152,
            "80.000000" : 561152,
            "90.000000" : 561152,
            "95.000000" : 561152,
            "99.000000" : 569344,
            "99.500000" : 577536,
            "99.900000" : 1384448,
            "99.950000" : 1712128,
            "99.990000" : 2670592
          }
        },
        "bw_min" : 110813,
        "bw_max" : 114789,
        "bw_agg" : 100.000000,
        "bw_mean" : 113867.642311,
        "bw_dev" : 595.127195,
        "bw_samples" : 1177,
        "iops_min" : 1731,
        "iops_max" : 1793,
        "iops_mean" : 1778.929482,
        "iops_stddev" : 9.291626,
        "iops_samples" : 1177
      },
      "ZNS Reset" : {
        "total_zone_resets" : 0,
        "io_bytes" : 0,
        "io_kbytes" : 0,
        "bw_bytes" : 0,
        "bw" : 0,
        "iops" : 0.000000,
        "runtime" : 0,
        "total_ios" : 0,
        "short_ios" : 0,
        "drop_ios" : 0,
        "slat_ns" : {
          "min" : 0,
          "max" : 0,
          "mean" : 0.000000,
          "stddev" : 0.000000,
          "N" : 0
        },
        "clat_ns" : {
          "min" : 0,
          "max" : 0,
          "mean" : 0.000000,
          "stddev" : 0.000000,
          "N" : 0
        },
        "lat_ns" : {
          "min" : 0,
          "max" : 0,
          "mean" : 0.000000,
          "stddev" : 0.000000,
          "N" : 0
        },
        "bw_min" : 0,
        "bw_max" : 0,
        "bw_agg" : 0.000000,
        "bw_mean" : 0.000000,
        "bw_dev" : 0.000000,
        "bw_samples" : 0,
        "iops_min" : 0,
        "iops_max" : 0,
        "iops_mean" : 0.000000,
        "iops_stddev" : 0.000000,
        "iops_samples" : 0
      },
      "sync" : {
        "total_ios" : 0,
        "lat_ns" : {
          "min" : 0,
          "max" : 0,
          "mean" : 0.000000,
          "stddev" : 0.000000,
          "N" : 0
        }
      },
      "job_runtime" : 589317,
      "usr_cpu" : 99.992703,
      "sys_cpu" : 0.000000,
      "ctx" : 724,
      "majf" : 0,
      "minf" : 0,
      "iodepth_level" : {
        "1" : 100.000000,
        "2" : 0.000000,
        "4" : 0.000000,
        "8" : 0.000000,
        "16" : 0.000000,
        "32" : 0.000000,
        ">=64" : 0.000000
      },
      "iodepth_submit" : {
        "0" : 0.000000,
        "4" : 100.000000,
        "8" : 0.000000,
        "16" : 0.000000,
        "32" : 0.000000,
        "64" : 0.000000,
        ">=64" : 0.000000
      },
      "iodepth_complete" : {
        "0" : 0.000000,
        "4" : 100.000000,
        "8" : 0.000000,
        "16" : 0.000000,
        "32" : 0.000000,
        "64" : 0.000000,
        ">=64" : 0.000000
      },
      "latency_ns" : {
        "2" : 0.000000,
        "4" : 0.000000,
        "10" : 0.000000,
        "20" : 0.000000,
        "50" : 0.000000,
        "100" : 0.000000,
        "250" : 0.000000,
        "500" : 0.000000,
        "750" : 0.000000,
        "1000" : 0.000000
      },
      "latency_us" : {
        "2" : 0.000000,
        "4" : 0.000000,
        "10" : 0.000000,
        "20" : 0.000000,
        "50" : 0.000000,
        "100" : 0.000000,
        "250" : 0.000000,
        "500" : 0.000000,
        "750" : 99.756193,
        "1000" : 0.024056
      },
      "latency_ms" : {
        "2" : 0.189871,
        "4" : 0.026920,
        "10" : 0.010000,
        "20" : 0.000000,
        "50" : 0.000000,
        "100" : 0.000000,
        "250" : 0.000000,
        "500" : 0.000000,
        "750" : 0.000000,
        "1000" : 0.000000,
        "2000" : 0.000000,
        ">=2000" : 0.000000
      },
      "latency_depth" : 1,
      "latency_target" : 0,
      "latency_percentile" : 100.000000,
      "latency_window" : 0
    },
    {
      "jobname" : "trim",
      "groupid" : 1,
      "error" : 0,
      "eta" : 0,
      "elapsed" : 592,
      "job options" : {
        "rw" : "randwrite",
        "iodepth" : "1",
        "size" : "1z",
        "offset" : "1023z",
        "flow_id" : "1",
        "flow" : "50"
      },
      "read" : {
        "io_bytes" : 0,
        "io_kbytes" : 0,
        "bw_bytes" : 0,
        "bw" : 0,
        "iops" : 0.000000,
        "runtime" : 0,
        "total_ios" : 0,
        "short_ios" : 0,
        "drop_ios" : 0,
        "slat_ns" : {
          "min" : 0,
          "max" : 0,
          "mean" : 0.000000,
          "stddev" : 0.000000,
          "N" : 0
        },
        "clat_ns" : {
          "min" : 0,
          "max" : 0,
          "mean" : 0.000000,
          "stddev" : 0.000000,
          "N" : 0
        },
        "lat_ns" : {
          "min" : 0,
          "max" : 0,
          "mean" : 0.000000,
          "stddev" : 0.000000,
          "N" : 0
        },
        "bw_min" : 0,
        "bw_max" : 0,
        "bw_agg" : 0.000000,
        "bw_mean" : 0.000000,
        "bw_dev" : 0.000000,
        "bw_samples" : 0,
        "iops_min" : 0,
        "iops_max" : 0,
        "iops_mean" : 0.000000,
        "iops_stddev" : 0.000000,
        "iops_samples" : 0
      },
      "write" : {
        "io_bytes" : 67108864,
        "io_kbytes" : 65536,
        "bw_bytes" : 52924971,
        "bw" : 51684,
        "iops" : 807.570978,
        "runtime" : 1268,
        "total_ios" : 1024,
        "short_ios" : 0,
        "drop_ios" : 0,
        "slat_ns" : {
          "min" : 0,
          "max" : 0,
          "mean" : 0.000000,
          "stddev" : 0.000000,
          "N" : 0
        },
        "clat_ns" : {
          "min" : 531302,
          "max" : 27798096,
          "mean" : 593430.403320,
          "stddev" : 868023.408555,
          "N" : 1024,
          "percentile" : {
            "1.000000" : 552960,
            "5.000000" : 552960,
            "10.000000" : 552960,
            "20.000000" : 552960,
            "30.000000" : 552960,
            "40.000000" : 552960,
            "50.000000" : 561152,
            "60.000000" : 561152,
            "70.000000" : 561152,
            "80.000000" : 561152,
            "90.000000" : 561152,
            "95.000000" : 561152,
            "99.000000" : 577536,
            "99.500000" : 634880,
            "99.900000" : 4554752,
            "99.950000" : 27918336,
            "99.990000" : 27918336
          }
        },
        "lat_ns" : {
          "min" : 532163,
          "max" : 27820301,
          "mean" : 595165.085937,
          "stddev" : 868661.226837,
          "N" : 1024,
          "percentile" : {
            "1.000000" : 552960,
            "5.000000" : 561152,
            "10.000000" : 561152,
            "20.000000" : 561152,
            "30.000000" : 561152,
            "40.000000" : 561152,
            "50.000000" : 561152,
            "60.000000" : 561152,
            "70.000000" : 561152,
            "80.000000" : 561152,
            "90.000000" : 561152,
            "95.000000" : 561152,
            "99.000000" : 577536,
            "99.500000" : 634880,
            "99.900000" : 4554752,
            "99.950000" : 27918336,
            "99.990000" : 27918336
          }
        },
        "bw_min" : 3968,
        "bw_max" : 66048,
        "bw_agg" : 67.733985,
        "bw_mean" : 35008.000000,
        "bw_dev" : 43897.188976,
        "bw_samples" : 2,
        "iops_min" : 62,
        "iops_max" : 1032,
        "iops_mean" : 547.000000,
        "iops_stddev" : 685.893578,
        "iops_samples" : 2
      },
      "ZNS Reset" : {
        "total_zone_resets" : 1023,
        "io_bytes" : 68652367872,
        "io_kbytes" : 67043328,
        "bw_bytes" : 99785418418,
        "bw" : 97446697,
        "iops" : 1486.918605,
        "runtime" : 688,
        "total_ios" : 1023,
        "short_ios" : 0,
        "drop_ios" : 0,
        "slat_ns" : {
          "min" : 0,
          "max" : 0,
          "mean" : 0.000000,
          "stddev" : 0.000000,
          "N" : 0
        },
        "clat_ns" : {
          "min" : 42675048752536,
          "max" : 42675701786546,
          "mean" : 42675342862516.960938,
          "stddev" : 152992372.715386,
          "N" : 1023,
          "percentile" : {
            "1.000000" : 17112760320,
            "5.000000" : 17112760320,
            "10.000000" : 17112760320,
            "20.000000" : 17112760320,
            "30.000000" : 17112760320,
            "40.000000" : 17112760320,
            "50.000000" : 17112760320,
            "60.000000" : 17112760320,
            "70.000000" : 17112760320,
            "80.000000" : 17112760320,
            "90.000000" : 17112760320,
            "95.000000" : 17112760320,
            "99.000000" : 17112760320,
            "99.500000" : 17112760320,
            "99.900000" : 17112760320,
            "99.950000" : 17112760320,
            "99.990000" : 17112760320
          }
        },
        "lat_ns" : {
          "min" : 2008339,
          "max" : 55912763,
          "mean" : 8671136.955034,
          "stddev" : 7296187.119459,
          "N" : 1023,
          "percentile" : {
            "1.000000" : 2007040,
            "5.000000" : 2023424,
            "10.000000" : 2072576,
            "20.000000" : 2146304,
            "30.000000" : 4046848,
            "40.000000" : 5865472,
            "50.000000" : 6062080,
            "60.000000" : 8028160,
            "70.000000" : 10027008,
            "80.000000" : 13959168,
            "90.000000" : 19791872,
            "95.000000" : 23724032,
            "99.000000" : 32112640,
            "99.500000" : 35913728,
            "99.900000" : 50069504,
            "99.950000" : 55836672,
            "99.990000" : 55836672
          }
        },
        "bw_min" : 123398930,
        "bw_max" : 123398930,
        "bw_agg" : 100.000000,
        "bw_mean" : 123398930.000000,
        "bw_dev" : 0.000000,
        "bw_samples" : 32,
        "iops_min" : 1881,
        "iops_max" : 1881,
        "iops_mean" : 1881.000000,
        "iops_stddev" : 0.000000,
        "iops_samples" : 32
      },
      "sync" : {
        "total_ios" : 0,
        "lat_ns" : {
          "min" : 0,
          "max" : 0,
          "mean" : 0.000000,
          "stddev" : 0.000000,
          "N" : 0
        }
      },
      "job_runtime" : 22316,
      "usr_cpu" : 24.910378,
      "sys_cpu" : 0.089622,
      "ctx" : 2181,
      "majf" : 0,
      "minf" : 0,
      "iodepth_level" : {
        "1" : 100.000000,
        "2" : 0.000000,
        "4" : 0.000000,
        "8" : 0.000000,
        "16" : 0.000000,
        "32" : 0.000000,
        ">=64" : 0.000000
      },
      "iodepth_submit" : {
        "0" : 0.000000,
        "4" : 100.000000,
        "8" : 0.000000,
        "16" : 0.000000,
        "32" : 0.000000,
        "64" : 0.000000,
        ">=64" : 0.000000
      },
      "iodepth_complete" : {
        "0" : 0.000000,
        "4" : 100.000000,
        "8" : 0.000000,
        "16" : 0.000000,
        "32" : 0.000000,
        "64" : 0.000000,
        ">=64" : 0.000000
      },
      "latency_ns" : {
        "2" : 0.000000,
        "4" : 0.000000,
        "10" : 0.000000,
        "20" : 0.000000,
        "50" : 0.000000,
        "100" : 0.000000,
        "250" : 0.000000,
        "500" : 0.000000,
        "750" : 0.000000,
        "1000" : 0.000000
      },
      "latency_us" : {
        "2" : 0.000000,
        "4" : 0.000000,
        "10" : 0.000000,
        "20" : 0.000000,
        "50" : 0.000000,
        "100" : 0.000000,
        "250" : 0.000000,
        "500" : 0.000000,
        "750" : 49.780166,
        "1000" : 0.000000
      },
      "latency_ms" : {
        "2" : 0.097704,
        "4" : 0.000000,
        "10" : 0.097704,
        "20" : 0.000000,
        "50" : 0.048852,
        "100" : 0.000000,
        "250" : 0.000000,
        "500" : 0.000000,
        "750" : 0.000000,
        "1000" : 0.000000,
        "2000" : 0.000000,
        ">=2000" : 49.975574
      },
      "latency_depth" : 1,
      "latency_target" : 0,
      "latency_percentile" : 100.000000,
      "latency_window" : 0
    }
  ]
}
